apitools/__init__.py
apitools/clients/__init__.py
apitools/clients/storage/__init__.py
apitools/clients/storage/storage_v1_client.py
apitools/clients/storage/storage_v1_messages.py
google_apitools_storage_v1-0.4.20150723.dist-info/DESCRIPTION.rst
google_apitools_storage_v1-0.4.20150723.dist-info/METADATA
google_apitools_storage_v1-0.4.20150723.dist-info/metadata.json
google_apitools_storage_v1-0.4.20150723.dist-info/RECORD
google_apitools_storage_v1-0.4.20150723.dist-info/top_level.txt
google_apitools_storage_v1-0.4.20150723.dist-info/WHEEL
