Metadata-Version: 2.0
Name: google-apitools-storage-v1
Version: 0.4.20150723
Summary: Autogenerated apitools library for storage
Home-page: https://github.com/google/apitools
Author: Craig Citro
Author-email: craigcitro@google.com
License: Apache 2.0
Keywords: apitools apitools-storage storage
Platform: UNKNOWN
Classifier: Programming Language :: Python :: 2.7
Classifier: License :: OSI Approved :: Apache Software License
Requires-Dist: google-apitools (>=0.4.8)
Requires-Dist: httplib2 (>=0.9)
Requires-Dist: oauth2client (>=1.4.12)
Requires-Dist: protorpc (>=0.10.0)
